fapistrano/__init__.py
fapistrano/app.py
fapistrano/cli.py
fapistrano/configuration.py
fapistrano/core.py
fapistrano/deploy.py
fapistrano/directory.py
fapistrano/envparse.py
fapistrano/signal.py
fapistrano/utils.py
fapistrano/plugins/__init__.py
fapistrano/plugins/curl.py
fapistrano/plugins/fis.py
fapistrano/plugins/git.py
fapistrano/plugins/git2slack.py
fapistrano/plugins/localshared.py
fapistrano/plugins/slack.py
fapistrano/plugins/supervisorctl.py
fapistrano/plugins/virtualenv.py
fapistrano/plugins/virtualenvtools.py
fapistrano/plugins/virtualenvwrapper.py
fapistrano-0.9.5.dist-info/DESCRIPTION.rst
fapistrano-0.9.5.dist-info/METADATA
fapistrano-0.9.5.dist-info/RECORD
fapistrano-0.9.5.dist-info/WHEEL
fapistrano-0.9.5.dist-info/entry_points.txt
fapistrano-0.9.5.dist-info/metadata.json
fapistrano-0.9.5.dist-info/top_level.txt
