Metadata-Version: 2.0
Name: fapistrano
Version: 0.9.5
Summary: A remote server automation and deployment tool.
Home-page: https://github.com/liwushuo/fapistrano
Author: Ju Lin
Author-email: soasme@gmail.com
License: MIT
Keywords: fapistrano,deploy,deployment,automate,automation,fabric,remote,production,staging,development
Platform: any
Classifier: Development Status :: 2 - Pre-Alpha
Classifier: Intended Audience :: Developers
Classifier: License :: OSI Approved :: MIT License
Classifier: Operating System :: OS Independent
Classifier: Programming Language :: Python
Classifier: Programming Language :: Python :: 2
Classifier: Programming Language :: Python :: 2.7
Requires-Dist: Fabric
Requires-Dist: PyYaml
Requires-Dist: click
Requires-Dist: requests
